LICENSE.txt
README.md
setup.py
easytradesdk/AbsContext.py
easytradesdk/AbsInstance.py
easytradesdk/AbsMarketApi.py
easytradesdk/AbsTradeApi.py
easytradesdk/Const.py
easytradesdk/Decorator.py
easytradesdk/Instance.py
easytradesdk/Serializer.py
easytradesdk/__init__.py
easytradesdk.egg-info/PKG-INFO
easytradesdk.egg-info/SOURCES.txt
easytradesdk.egg-info/dependency_links.txt
easytradesdk.egg-info/requires.txt
easytradesdk.egg-info/top_level.txt
easytradesdk/entity/Depth.py
easytradesdk/entity/Kline.py
easytradesdk/entity/Order.py
easytradesdk/entity/Position.py
easytradesdk/entity/Slippage.py
easytradesdk/entity/Ticker.py
easytradesdk/entity/__init__.py
easytradesdk/indicator/Boll.py
easytradesdk/indicator/Cci.py
easytradesdk/indicator/Ema.py
easytradesdk/indicator/Ma.py
easytradesdk/indicator/Macd.py
easytradesdk/indicator/Rsi.py
easytradesdk/indicator/SimpleIndicator.py
easytradesdk/indicator/Wma.py
easytradesdk/indicator/__init__.py
easytradesdk/support/Condition.py
easytradesdk/support/Conditions.py
easytradesdk/support/Supporter.py
easytradesdk/support/__init__.py